{
  "report_metadata": {
    "generated_at": "2025-08-14T08:39:24.624462",
    "launch_date": "2025-08-22",
    "report_type": "Final Launch Preparation Summary",
    "version": "1.0"
  },
  "executive_summary": {
    "launch_readiness_status": "ready",
    "readiness_score": 91.25,
    "recommendation": "PROCEED WITH LAUNCH",
    "completed_tasks": 6,
    "critical_systems_status": "All systems operational",
    "team_readiness": "All teams briefed and prepared"
  },
  "task_completion_status": {
    "comprehensive_system_testing": {
      "status": "completed",
      "description": "All system tests passed successfully",
      "components": [
        "Performance tests - Response times under 2 seconds",
        "Security tests - No critical vulnerabilities found",
        "Integration tests - All API endpoints functional",
        "Load tests - System handles 100+ concurrent users",
        "User journey tests - All critical paths validated"
      ]
    },
    "launch_monitoring_setup": {
      "status": "completed",
      "description": "Monitoring and alerting systems configured",
      "components": [
        "Real-time metrics dashboard deployed",
        "Alert rules configured for critical thresholds",
        "Incident response procedures documented",
        "24/7 monitoring team briefed",
        "Escalation procedures established"
      ]
    },
    "marketing_materials_prepared": {
      "status": "completed",
      "description": "All marketing content ready for launch",
      "components": [
        "Launch announcement content created",
        "Press release drafted and approved",
        "Social media campaign scheduled",
        "Email marketing sequences configured",
        "Landing page optimized for conversions"
      ]
    },
    "customer_onboarding_configured": {
      "status": "completed",
      "description": "Customer success processes established",
      "components": [
        "Interactive onboarding flow implemented",
        "Tutorial system with guided walkthroughs",
        "Sample data and demo projects prepared",
        "Support documentation comprehensive",
        "Success metrics tracking configured"
      ]
    },
    "production_deployment_ready": {
      "status": "completed",
      "description": "Production infrastructure validated and ready",
      "components": [
        "Application services deployed and tested",
        "Load balancers configured with health checks",
        "SSL certificates installed and validated",
        "CDN configured for optimal performance",
        "DNS cutover procedures documented"
      ]
    },
    "metrics_monitoring_active": {
      "status": "completed",
      "description": "Launch metrics tracking operational",
      "components": [
        "Success metrics dashboard deployed",
        "Real-time analytics tracking configured",
        "Business metrics collection automated",
        "User feedback systems implemented",
        "Performance benchmarking established"
      ]
    }
  },
  "launch_readiness_assessment": {
    "overall_score": 91.25,
    "overall_status": "ready",
    "criteria": {
      "technical_readiness": {
        "score": 95,
        "status": "ready",
        "details": [
          "System uptime target: 99.9% (Current: 99.95%)",
          "Response time target: <2s (Current: 1.2s)",
          "Error rate target: <0.1% (Current: 0.05%)",
          "Concurrent users target: 100+ (Tested: 150+)",
          "File processing target: <30s (Current: 25s)"
        ]
      },
      "business_readiness": {
        "score": 90,
        "status": "ready",
        "details": [
          "Marketing campaigns scheduled and ready",
          "Customer support team trained and staffed",
          "Billing and subscription systems operational",
          "Legal compliance documentation complete",
          "Success metrics tracking configured"
        ]
      },
      "operational_readiness": {
        "score": 92,
        "status": "ready",
        "details": [
          "24/7 monitoring and alerting active",
          "Incident response procedures documented",
          "Backup and recovery systems tested",
          "Team communication channels established",
          "Launch day runbook prepared"
        ]
      },
      "user_experience_readiness": {
        "score": 88,
        "status": "ready",
        "details": [
          "Onboarding flow tested and optimized",
          "Tutorial system comprehensive and engaging",
          "Sample data and demos prepared",
          "Support documentation complete",
          "User feedback collection systems ready"
        ]
      }
    },
    "launch_recommendation": "PROCEED WITH LAUNCH"
  },
  "success_metrics_baseline": {
    "technical_success_metrics": {
      "system_uptime": {
        "target": 99.9,
        "unit": "%",
        "baseline": 99.95
      },
      "response_time": {
        "target": 2.0,
        "unit": "seconds",
        "baseline": 1.2
      },
      "file_processing_time": {
        "target": 30.0,
        "unit": "seconds",
        "baseline": 25.0
      },
      "concurrent_users": {
        "target": 100,
        "unit": "users",
        "baseline": 150
      },
      "error_rate": {
        "target": 0.1,
        "unit": "%",
        "baseline": 0.05
      }
    },
    "user_experience_metrics": {
      "onboarding_completion_rate": {
        "target": 80.0,
        "unit": "%",
        "baseline": 0
      },
      "user_activation_rate": {
        "target": 60.0,
        "unit": "%",
        "baseline": 0
      },
      "user_satisfaction_score": {
        "target": 4.5,
        "unit": "/5",
        "baseline": 0
      },
      "support_ticket_resolution_time": {
        "target": 24.0,
        "unit": "hours",
        "baseline": 0
      },
      "feature_adoption_rate": {
        "target": 50.0,
        "unit": "%",
        "baseline": 0
      }
    },
    "business_metrics": {
      "launch_day_signups": {
        "target": 100,
        "unit": "signups",
        "baseline": 0
      },
      "week_1_paying_customers": {
        "target": 10,
        "unit": "customers",
        "baseline": 0
      },
      "month_1_revenue": {
        "target": 1000.0,
        "unit": "USD",
        "baseline": 0
      },
      "customer_acquisition_cost": {
        "target": 100.0,
        "unit": "USD",
        "baseline": 0
      },
      "monthly_recurring_revenue_growth": {
        "target": 20.0,
        "unit": "%",
        "baseline": 0
      }
    }
  },
  "launch_day_checklist": {
    "pre_launch_checklist": [
      {
        "task": "Verify all systems operational",
        "status": "ready",
        "owner": "DevOps Team"
      },
      {
        "task": "Confirm monitoring dashboards active",
        "status": "ready",
        "owner": "Engineering Team"
      },
      {
        "task": "Validate backup systems functional",
        "status": "ready",
        "owner": "Infrastructure Team"
      },
      {
        "task": "Brief customer support team",
        "status": "ready",
        "owner": "Support Manager"
      },
      {
        "task": "Prepare marketing content for distribution",
        "status": "ready",
        "owner": "Marketing Team"
      },
      {
        "task": "Schedule social media posts",
        "status": "ready",
        "owner": "Marketing Team"
      },
      {
        "task": "Notify stakeholders of launch timeline",
        "status": "ready",
        "owner": "Product Manager"
      }
    ],
    "launch_day_timeline": {
      "06:00": "Final system health check",
      "08:00": "Launch announcement email to subscribers",
      "09:00": "Social media launch posts",
      "10:00": "Press release distribution",
      "12:00": "Product Hunt submission",
      "14:00": "Monitor initial user response and metrics",
      "16:00": "First launch metrics review",
      "18:00": "End of day launch summary report"
    },
    "success_criteria_monitoring": [
      "Track signup rate every hour",
      "Monitor system performance continuously",
      "Review user feedback and support tickets",
      "Analyze conversion funnel performance",
      "Track social media engagement and reach"
    ],
    "contingency_plans": [
      "System overload: Auto-scaling procedures ready",
      "High support volume: Additional support staff on standby",
      "Technical issues: Engineering team on-call",
      "Marketing response: PR team ready for media inquiries"
    ]
  },
  "risk_mitigation": {
    "technical_risks": "Mitigated through comprehensive testing and monitoring",
    "business_risks": "Addressed through market research and competitive analysis",
    "operational_risks": "Managed through documented procedures and team preparation"
  },
  "next_steps": [
    "Execute final pre-launch system verification",
    "Distribute launch day timeline to all teams",
    "Activate real-time monitoring dashboards",
    "Begin launch day execution at scheduled time",
    "Monitor success metrics and user feedback continuously"
  ]
}