{"timestamp": "2025-07-26T06:12:31.511444", "level": "INFO", "logger": "scrollintel.security", "message": "Security event: login_attempt", "event_type": "login_attempt", "user_id": "test_user", "ip": "127.0.0.1", "module": "logging_config", "function": "log_security_event", "line": 276, "process_id": 12792, "thread_id": 20192}
{"timestamp": "2025-07-26T06:12:31.515029", "level": "INFO", "logger": "scrollintel.audit", "message": "Audit: user_action - read on test_resource", "event_type": "user_action", "user_id": "test_user", "resource": "test_resource", "action": "read", "details": {"details": "test"}, "module": "logging_config", "function": "log_audit_event", "line": 306, "process_id": 12792, "thread_id": 20192}
{"timestamp": "2025-07-26T06:13:09.609369", "level": "INFO", "logger": "scrollintel.security", "message": "Security event: login_attempt", "event_type": "login_attempt", "user_id": "test_user", "ip": "127.0.0.1", "module": "logging_config", "function": "log_security_event", "line": 276, "process_id": 14236, "thread_id": 10836}
{"timestamp": "2025-07-26T06:13:09.610186", "level": "INFO", "logger": "scrollintel.audit", "message": "Audit: user_action - read on test_resource", "event_type": "user_action", "user_id": "test_user", "resource": "test_resource", "action": "read", "details": {"details": "test"}, "module": "logging_config", "function": "log_audit_event", "line": 306, "process_id": 14236, "thread_id": 10836}
